spotify2ytmusic/__init__.py
spotify2ytmusic/__main__.py
spotify2ytmusic/backend.py
spotify2ytmusic/cli.py
spotify2ytmusic/gui.py
spotify2ytmusic/reverse_playlist.py
spotify2ytmusic/settings.json
spotify2ytmusic/spotify_backup.py
spotify2ytmusic/ytmusic_credentials.py
spotify2ytmusic-0.9.32.dist-info/LICENSE
spotify2ytmusic-0.9.32.dist-info/METADATA
spotify2ytmusic-0.9.32.dist-info/WHEEL
spotify2ytmusic-0.9.32.dist-info/entry_points.txt
spotify2ytmusic-0.9.32.dist-info/RECORD
