Metadata-Version: 2.3
Name: spotify2ytmusic
Version: 0.9.32
Summary: Copy Spotify playlists to YTMusic/YouTube Music
License: CC0-1.0
Author: Sean Reifschneider
Author-email: jafo00@gmail.com
Requires-Python: >=3.10,<4.0
Classifier: License :: CC0 1.0 Universal (CC0 1.0) Public Domain Dedication
Classifier: Programming Language :: Python :: 3
Classifier: Programming Language :: Python :: 3.10
Classifier: Programming Language :: Python :: 3.11
Classifier: Programming Language :: Python :: 3.12
Classifier: Programming Language :: Python :: 3.13
Requires-Dist: ytmusicapi
